{
  "required": true,
  "package": "ca.stellardrift.permissionsex.fabric.mixin",
  "plugin": "ca.stellardrift.permissionsex.fabric.impl.PermissionsExMixinsPlugin",
  "compatibilityLevel": "JAVA_8",
  "mixins": [
    "check.ArgumentBuilderMixin",
    "check.BlockItemMixin",
    "check.CommandBlockExecutorMixin",
    "check.CommandBlockItemMixin",
    "check.DebugStickItemMixin",
    "check.DedicatedPlayerManagerMixin",
    "check.DedicatedServerMixin",
    "check.EntityArgumentTypeMixin",
    "check.EntitySelectorMixin",
    "check.EntityTypeMixin",
    "check.MessageArgumentTypeMixin",
    "check.PlayerManagerMixin",
    "check.ServerCommandSourceMixin",
    "check.ServerPlayerEntityMixin",
    "check.ServerPlayerInteractionManagerMixin",
    "check.ServerPlayNetworkHandlerMixin",
    "check.StructureBlockEntityMixin",
    "lifecycle.ClientConnectionMixin",
    "lifecycle.GameProfileMixin",
    "lifecycle.MinecraftDedicatedServerMixin",
    "lifecycle.ServerHandshakeNetworkHandlerMixin",
    "source.CommandBlockExecutorMixin",
    "source.CommandFunctionFunctionElementMixin",
    "source.CommandFunctionManagerMixin",
    "source.FunctionLoaderMixin",
    "source.RconCommandOutputMixin",
    "source.ServerCommandSourceMixin",
    "source.ServerPlayerEntityMixin"
  ],
  "client": [
    "lifecycle.MinecraftClientMixin"
  ],
  "injectors": {
    "defaultRequire": 1
  }
}
